karp5/__init__.py
karp5/backend.py
karp5/errors.py
karp5/instance_info.py
karp5/main.py
karp5/application/__init__.py
karp5/application/actions/__init__.py
karp5/application/actions/mode_actions.py
karp5/cli/__init__.py
karp5/cli/create_metadata.py
karp5/cli/getmapping.py
karp5/cli/upload_offline.py
karp5/config/__init__.py
karp5/config/config.py
karp5/config/configmanager.py
karp5/config/errors.py
karp5/config/ext/__init__.py
karp5/config/ext/ext_src.py
karp5/context/__init__.py
karp5/context/auth/__init__.py
karp5/context/auth/dummy_auth.py
karp5/context/auth/std_auth.py
karp5/dbhandler/__init__.py
karp5/dbhandler/dbhandler.py
karp5/dbhandler/emailsender.py
karp5/document/__init__.py
karp5/document/autoupdates.py
karp5/document/doc_converter.py
karp5/domain/__init__.py
karp5/domain/model/__init__.py
karp5/domain/model/mode.py
karp5/domain/model/user.py
karp5/domain/services/__init__.py
karp5/domain/services/search_service.py
karp5/html/api.md
karp5/html/index_dokumentation.html
karp5/infrastructure/json_file_mode_repository.py
karp5/server/__init__.py
karp5/server/checkdbhistory.py
karp5/server/extensions.py
karp5/server/idgenerator.py
karp5/server/searching.py
karp5/server/suggestions.py
karp5/server/update.py
karp5/server/helper/__init__.py
karp5/server/helper/flaskhelper.py
karp5/server/helper/helpers.py
karp5/server/helper/jsonwalk.py
karp5/server/translator/__init__.py
karp5/server/translator/bulkify.py
karp5/server/translator/elasticObjects.py
karp5/server/translator/errors.py
karp5/server/translator/parser.py
karp5/server/translator/validatejson.py
karp5/static/api.css
karp5/static/karp.png
karp5/tests/_test_config.py
karp5/tests/auth_server.py
karp5/tests/common_fixtures.py
karp5/tests/conftest.py
karp5/tests/test_index.py
karp5/tests/test_modes.py
karp5/tests/test_update_index.py
karp5/tests/util.py
karp5/tests/api/__init__.py
karp5/tests/api/test_autocomplete.py
karp5/tests/api/test_explain.py
karp5/tests/api/test_export.py
karp_backend_5-5.29.0.dist-info/LICENSE
karp_backend_5-5.29.0.dist-info/METADATA
karp_backend_5-5.29.0.dist-info/WHEEL
karp_backend_5-5.29.0.dist-info/pbr.json
karp_backend_5-5.29.0.dist-info/top_level.txt
karp_backend_5-5.29.0.dist-info/RECORD
