Metadata-Version: 2.1
Name: karp-backend-5
Version: 5.29.0
Summary: Backend for Karp
Home-page: https://github.com/spraakbanken/karp-backend-v5
Author: Språkbanken at the University of Gothenburg
Author-email: sb-info@svenska.gu.se
Maintainer: Språkbanken
Maintainer-email: sb-info@svenska.gu.se
License: MIT
Project-URL: Bug Tracker, https://github.com/spraakbanken/karp-backend-v5/issues
Project-URL: Source Code, https://github.com/spraakbanken/karp-backend-v5
Classifier: Development Status :: 5 - Production/Stable
Classifier: Intended Audience :: Developers
Classifier: License :: OSI Approved :: MIT License
Classifier: Operating System :: Unix
Classifier: Operating System :: POSIX
Classifier: Programming Language :: Python
Classifier: Programming Language :: Python :: 3
Classifier: Programming Language :: Python :: 3.6
Classifier: Programming Language :: Python :: 3.7
Classifier: Programming Language :: Python :: 3.8
Classifier: Programming Language :: Python :: Implementation :: CPython
Classifier: Topic :: Utilities
License-File: LICENSE
Requires-Dist: elasticsearch <7.0.0,>=6.1.0
Requires-Dist: elasticsearch-dsl <7.0.0,>=6.0.0
Requires-Dist: Flask
Requires-Dist: SQLAlchemy <2
Requires-Dist: urllib3
Requires-Dist: six
Requires-Dist: pymysql
Requires-Dist: markdown
Requires-Dist: python-dotenv
Requires-Dist: sb-json-tools >=0.4.3
Requires-Dist: json-streams
Requires-Dist: flask-matomo2
Provides-Extra: dev
Requires-Dist: black ; extra == 'dev'
Requires-Dist: bump2version ; extra == 'dev'
Provides-Extra: test
Requires-Dist: pytest ; extra == 'test'
Requires-Dist: pytest-cov ; extra == 'test'
Requires-Dist: codecov ; extra == 'test'
Requires-Dist: elasticsearch-test-py ; extra == 'test'
Requires-Dist: pylint ; extra == 'test'
Requires-Dist: hypothesis ; extra == 'test'
Requires-Dist: attrs >=19.2 ; extra == 'test'
Requires-Dist: flake8 ; extra == 'test'
